quantfactortest.py
IDEAfactortest-1.2.dist-info/METADATA
IDEAfactortest-1.2.dist-info/WHEEL
IDEAfactortest-1.2.dist-info/top_level.txt
IDEAfactortest-1.2.dist-info/RECORD
